README.md
setup.py
varunmurthy/__init__.py
varunmurthy/me.py
varunmurthy.egg-info/PKG-INFO
varunmurthy.egg-info/SOURCES.txt
varunmurthy.egg-info/dependency_links.txt
varunmurthy.egg-info/top_level.txt