Metadata-Version: 2.1
Name: varunmurthy
Version: 0.0.2
Summary: Mr. Murthy's professional information at your fingertips.
Home-page: https://github.com/Murthy1999/varunmurthy
Author: Varun Murthy
Author-email: murthy@berkeley.edu
License: UNKNOWN
Platform: UNKNOWN
Classifier: Programming Language :: Python :: 3
Classifier: License :: OSI Approved :: GNU General Public License v3 (GPLv3)
Classifier: Operating System :: OS Independent
